Metadata-Version: 1.2
Name: rxsci-river
Version: 0.1.0
Summary: River-Ml integration into RxSci
Home-page: https://github.com/maki-nage/rxsci-river.git
Author: Romain Picard
Author-email: romain.picard@oakbits.com
License: MIT
Project-URL: Documentation, https://www.makinage.org/doc/rxsci-river/latest/index.html
Platform: any
Classifier: Development Status :: 3 - Alpha
Classifier: License :: OSI Approved :: MIT License
Classifier: Intended Audience :: Developers
Classifier: Programming Language :: Python :: 3
Classifier: Topic :: Scientific/Engineering :: Artificial Intelligence
